CHANGELOG.txt
LICENSES.txt
MANIFEST.in
README.txt
setup.py
SpokenToWrittenConvert/__init__.py
SpokenToWrittenConvert/conversion.py
SpokenToWrittenConvert.egg-info/PKG-INFO
SpokenToWrittenConvert.egg-info/SOURCES.txt
SpokenToWrittenConvert.egg-info/dependency_links.txt
SpokenToWrittenConvert.egg-info/requires.txt
SpokenToWrittenConvert.egg-info/top_level.txt