Metadata-Version: 1.2
Name: SpokenToWrittenConvert
Version: 0.0.1
Summary: Spoken english to written english convertor
Home-page: UNKNOWN
Author: MOHIT CHVK
Author-email: mohit.chvk@gmail.com
License: MIT
Keywords: convertor
Platform: UNKNOWN
Classifier: Development Status :: 5 - Production/Stable
Classifier: Intended Audience :: Education
Classifier: Operating System :: Microsoft :: Windows :: Windows 10
Classifier: License :: OSI Approved :: MIT License
Classifier: Programming Language :: Python :: 3
Requires-Python: >=3.6
